video_summary/__init__.py
video_summary/sdk.py
video_summary-1.0.3.dist-info/LICENSE
video_summary-1.0.3.dist-info/METADATA
video_summary-1.0.3.dist-info/WHEEL
video_summary-1.0.3.dist-info/top_level.txt
video_summary-1.0.3.dist-info/RECORD
