Metadata-Version: 2.1
Name: video-summary
Version: 1.0.3
Summary: A Python SDK for video processing, providing functionalities like speech-to-text, summarization, transcription, and chaptering.
Home-page: https://github.com/Video-Summary/video-summary-python-sdk
Author: Video Summary
Author-email: hi@videosummary.io
Project-URL: Documentation, https://github.com/Video-Summary/video-summary-python-sdk#readme
Project-URL: Source, https://github.com/Video-Summary/video-summary-python-sdk
Project-URL: Tracker, https://github.com/Video-Summary/video-summary-python-sdk/issues
Keywords: video processing,speech-to-text,video summarization,transcription,chaptering
Classifier: Development Status :: 4 - Beta
Classifier: Intended Audience :: Developers
Classifier: Natural Language :: English
Classifier: License :: OSI Approved :: MIT License
Classifier: Programming Language :: Python :: 3
Classifier: Programming Language :: Python :: 3.6
Classifier: Programming Language :: Python :: 3.7
Classifier: Programming Language :: Python :: 3.8
Classifier: Programming Language :: Python :: 3.9
Classifier: Programming Language :: Python :: 3.10
Classifier: Operating System :: OS Independent
Requires-Python: >=3.6
License-File: LICENSE
Requires-Dist: requests >=2.25.1
